overlay_maintain_tools/__init__.py
overlay_maintain_tools/__main__.py
overlay_maintain_tools/check_remote_versions.py
overlay_maintain_tools/fs_utils.py
overlay_maintain_tools/main.py
overlay_maintain_tools/main_helpers.py
overlay_maintain_tools/mkreadme.py
overlay_maintain_tools/pkgs_cache.py
overlay_maintain_tools/version_utils.py
overlay_maintain_tools/data/_overlay_maintain_tools.bash_completion
overlay_maintain_tools/data/_overlay_maintain_tools.zsh_completion
overlay_maintain_tools/data/sample_readme.skel.jinja2
overlay_maintain_tools/repology/__init__.py
overlay_maintain_tools/repology/main.py
overlay_maintain_tools-1.3.1.dist-info/LICENSE
overlay_maintain_tools-1.3.1.dist-info/METADATA
overlay_maintain_tools-1.3.1.dist-info/WHEEL
overlay_maintain_tools-1.3.1.dist-info/entry_points.txt
overlay_maintain_tools-1.3.1.dist-info/top_level.txt
overlay_maintain_tools-1.3.1.dist-info/RECORD
