Metadata-Version: 2.1
Name: overlay-maintain-tools
Version: 1.3.1
Summary: A set of utilities to maintain Gentoo overlay
Home-page: https://github.com/VTimofeenko/overlay-maintain-tools
Author: Vladimir Timofeenko
Author-email: overlay.tools.maintain@vtimofeenko.com
License: GPL
Project-URL: Bug Reports, https://github.com/VTimofeenko/overlay-maintain-tools/issues
Project-URL: Source, https://github.com/VTimofeenko/overlay-maintain-tools
Keywords: gentoo overlay
Platform: UNKNOWN
Classifier: Development Status :: 4 - Beta
Classifier: Environment :: Console
Classifier: Topic :: Utilities
Classifier: Programming Language :: Python :: 3.8
Classifier: License :: OSI Approved :: GNU General Public License v3 (GPLv3)
Requires-Python: >=3.8, <4
Requires-Dist: python-dotenv (>=0.15.0)
Requires-Dist: requests (~=2.25.1)
Requires-Dist: typer (~=0.3.2)
Requires-Dist: toolz (~=0.11.1)
Requires-Dist: jinja2
Requires-Dist: portage
Requires-Dist: libversion
Provides-Extra: docs
Requires-Dist: jinja2 ; extra == 'docs'
Requires-Dist: typer-cli ; extra == 'docs'
